xslim/__init__.py
xslim/__main__.py
xslim/calibration_helper.py
xslim/defs.py
xslim/logger.py
xslim/onnx_graph_helper.py
xslim/xslim_pipeline.py
xslim/xslim_setting.py
xslim/analyse/__init__.py
xslim/analyse/graphwise.py
xslim/onnxslim_pass/__init__.py
xslim/onnxslim_pass/dynamic_q_matmul.py
xslim/onnxslim_pass/gelu.py
xslim/onnxslim_pass/layernorm.py
xslim/optimizer/__init__.py
xslim/optimizer/calibration.py
xslim/optimizer/equalization.py
xslim/optimizer/fusion.py
xslim/optimizer/legalized.py
xslim/optimizer/observer.py
xslim/optimizer/refine.py
xslim/optimizer/training.py
xslim/ppq_decorator/__init__.py
xslim/ppq_decorator/ppq/__init__.py
xslim/ppq_decorator/ppq/IR/__init__.py
xslim/ppq_decorator/ppq/IR/deploy.py
xslim/ppq_decorator/ppq/IR/morph.py
xslim/ppq_decorator/ppq/IR/processer.py
xslim/ppq_decorator/ppq/IR/quantize.py
xslim/ppq_decorator/ppq/IR/search.py
xslim/ppq_decorator/ppq/IR/training.py
xslim/ppq_decorator/ppq/IR/base/__init__.py
xslim/ppq_decorator/ppq/IR/base/command.py
xslim/ppq_decorator/ppq/IR/base/graph.py
xslim/ppq_decorator/ppq/IR/base/opdef.py
xslim/ppq_decorator/ppq/core/__init__.py
xslim/ppq_decorator/ppq/core/common.py
xslim/ppq_decorator/ppq/core/config.py
xslim/ppq_decorator/ppq/core/data.py
xslim/ppq_decorator/ppq/core/defs.py
xslim/ppq_decorator/ppq/core/ffi.py
xslim/ppq_decorator/ppq/core/quant.py
xslim/ppq_decorator/ppq/core/storage.py
xslim/ppq_decorator/ppq/executor/__init__.py
xslim/ppq_decorator/ppq/executor/base.py
xslim/ppq_decorator/ppq/executor/torch.py
xslim/ppq_decorator/ppq/executor/op/__init__.py
xslim/ppq_decorator/ppq/executor/op/torch/__init__.py
xslim/ppq_decorator/ppq/executor/op/torch/base.py
xslim/ppq_decorator/ppq/executor/op/torch/default.py
xslim/ppq_decorator/ppq/executor/op/torch/xslim_qfunction.py
xslim/ppq_decorator/ppq/parser/__init__.py
xslim/ppq_decorator/ppq/parser/native.py
xslim/ppq_decorator/ppq/parser/onnx_exporter.py
xslim/ppq_decorator/ppq/parser/onnx_parser.py
xslim-2.0.6.dist-info/LICENSE
xslim-2.0.6.dist-info/METADATA
xslim-2.0.6.dist-info/WHEEL
xslim-2.0.6.dist-info/top_level.txt
xslim-2.0.6.dist-info/RECORD
