Metadata-Version: 2.1
Name: xslim
Version: 2.0.6
Summary: XSlim is an offline quantization tools based on PPQ
Home-page: UNKNOWN
Author: SpacemiT
Author-email: xslim@spacemit.com
License: Apache License
Platform: UNKNOWN
Classifier: Development Status :: 3 - Alpha
Classifier: License :: OSI Approved :: Apache Software License
Classifier: Operating System :: OS Independent
Classifier: Programming Language :: Python :: 3
Requires-Python: >=3.6
License-File: LICENSE
Requires-Dist: loguru
Requires-Dist: numpy (>=2.0.0)
Requires-Dist: nvidia-pyindex
Requires-Dist: onnx-graphsurgeon
Requires-Dist: onnx (<1.17.0,>=1.16.0)
Requires-Dist: onnxconverter-common (>=1.14.0)
Requires-Dist: onnxruntime (<1.21.0,>=1.20.1)
Requires-Dist: onnxslim (>=0.1.61)
Requires-Dist: opencv-python
Requires-Dist: pandas
Requires-Dist: protobuf
Requires-Dist: sympy (>=1.12.0)
Requires-Dist: tabulate
Requires-Dist: torch (>=2.0.0)
Requires-Dist: torchvision
Requires-Dist: tqdm
